odoo/addons/ladirecta_odoo_keycloak_connector/README.md
odoo/addons/ladirecta_odoo_keycloak_connector/__init__.py
odoo/addons/ladirecta_odoo_keycloak_connector/__manifest__.py
odoo/addons/ladirecta_odoo_keycloak_connector/listeners/__init__.py
odoo/addons/ladirecta_odoo_keycloak_connector/listeners/contract_listener.py
odoo/addons/ladirecta_odoo_keycloak_connector/models/__init__.py
odoo/addons/ladirecta_odoo_keycloak_connector/models/company.py
odoo/addons/ladirecta_odoo_keycloak_connector/models/contract_contract.py
odoo/addons/ladirecta_odoo_keycloak_connector/models/res_partner.py
odoo/addons/ladirecta_odoo_keycloak_connector/services/__init__.py
odoo/addons/ladirecta_odoo_keycloak_connector/services/keycloak.py
odoo/addons/ladirecta_odoo_keycloak_connector/views/res_company.xml
odoo/addons/ladirecta_odoo_keycloak_connector/views/res_partner.xml
odoo_addon_ladirecta_odoo_keycloak_connector-16.0.1.1.2.dist-info/METADATA
odoo_addon_ladirecta_odoo_keycloak_connector-16.0.1.1.2.dist-info/WHEEL
odoo_addon_ladirecta_odoo_keycloak_connector-16.0.1.1.2.dist-info/top_level.txt
odoo_addon_ladirecta_odoo_keycloak_connector-16.0.1.1.2.dist-info/RECORD
